Metadata-Version: 1.0
Name: minecraft.py
Version: 0.1
Summary: Minecraft API
Home-page: https://github.com/IkumiGames/mc-api-py
Author: William Evans
Author-email: w@william.gg
License: UNKNOWN
Platform: UNKNOWN
